acwa_trainer/__init__.py
acwa_trainer/acwa_trainer.py
acwa_trainer-1.0.0.dist-info/licenses/LICENSE
cbam_resnet/__init__.py
cbam_resnet/cbam_resnet.py
hybrid_loss/__init__.py
hybrid_loss/hybrid_loss.py
improved_model/__init__.py
improved_model/acwa_model.py
acwa_trainer-1.0.0.dist-info/METADATA
acwa_trainer-1.0.0.dist-info/WHEEL
acwa_trainer-1.0.0.dist-info/top_level.txt
acwa_trainer-1.0.0.dist-info/RECORD
