Metadata-Version: 2.4
Name: acwa-trainer
Version: 1.0.0
Summary: Adaptive Class Weight Adjustment (ACWA) for Imbalanced Deep Learning
Home-page: https://github.com/Seread335/Thu-t-To-n-Adaptive-Class-Weight-Adjustment-ACWA-.git
Author: Huynh Thai Bao
Author-email: seread335@gmail.com
Classifier: Programming Language :: Python :: 3
Classifier: License :: OSI Approved :: MIT License
Classifier: Operating System :: OS Independent
Requires-Python: >=3.7
License-File: LICENSE
Requires-Dist: torch
Requires-Dist: torchvision
Requires-Dist: torchmetrics
Requires-Dist: numpy
Requires-Dist: scikit-learn
Requires-Dist: matplotlib
Dynamic: author
Dynamic: author-email
Dynamic: classifier
Dynamic: description
Dynamic: description-content-type
Dynamic: home-page
Dynamic: license-file
Dynamic: requires-dist
Dynamic: requires-python
Dynamic: summary
